hmd_lib_telemetry/__init__.py
hmd_lib_telemetry/hmd_lib_telemetry.py
hmd_lib_telemetry/lambda_decorators.py
hmd_lib_telemetry-0.1.51.dist-info/METADATA
hmd_lib_telemetry-0.1.51.dist-info/WHEEL
hmd_lib_telemetry-0.1.51.dist-info/top_level.txt
hmd_lib_telemetry-0.1.51.dist-info/RECORD
