Metadata-Version: 2.1
Name: hmd-lib-telemetry
Version: 0.1.51
Summary: Functions to instrument NeuronSphere services with OpenTelemetry
Author: Alex Burgoon
Author-email: alex.burgoon@hmdlabs.io
License: unlicensed
Requires-Dist: certifi==2025.4.26
Requires-Dist: charset-normalizer==2.0.12
Requires-Dist: googleapis-common-protos==1.70.0
Requires-Dist: grpcio==1.75.1
Requires-Dist: idna==3.10
Requires-Dist: importlib-metadata==8.7.0
Requires-Dist: opentelemetry-api==1.34.0
Requires-Dist: opentelemetry-exporter-otlp-proto-common==1.34.0
Requires-Dist: opentelemetry-exporter-otlp-proto-grpc==1.34.0
Requires-Dist: opentelemetry-exporter-otlp-proto-http==1.34.0
Requires-Dist: opentelemetry-instrumentation==0.55b0
Requires-Dist: opentelemetry-instrumentation-logging==0.55b0
Requires-Dist: opentelemetry-proto==1.34.0
Requires-Dist: opentelemetry-sdk==1.34.0
Requires-Dist: opentelemetry-semantic-conventions==0.55b0
Requires-Dist: packaging==25.0
Requires-Dist: protobuf==5.29.5
Requires-Dist: requests==2.32.3
Requires-Dist: typing-extensions==4.15.0
Requires-Dist: urllib3==1.26.8
Requires-Dist: wrapt==1.17.3
Requires-Dist: zipp==3.23.0
